wrlc/alma/api_client/__init__.py
wrlc/alma/api_client/api/__init__.py
wrlc/alma/api_client/api/analytics.py
wrlc/alma/api_client/api/bib.py
wrlc/alma/api_client/api/holding.py
wrlc/alma/api_client/api/item.py
wrlc/alma/api_client/client.py
wrlc/alma/api_client/exceptions.py
wrlc/alma/api_client/models/__init__.py
wrlc/alma/api_client/models/analytics.py
wrlc/alma/api_client/models/bib.py
wrlc/alma/api_client/models/holding.py
wrlc/alma/api_client/models/item.py
wrlc/alma/api_client/models/utils.py
wrlc_alma_api_client-0.1.13.dist-info/LICENSE
wrlc_alma_api_client-0.1.13.dist-info/METADATA
wrlc_alma_api_client-0.1.13.dist-info/WHEEL
wrlc_alma_api_client-0.1.13.dist-info/RECORD
