Metadata-Version: 2.3
Name: wrlc-alma-api-client
Version: 0.1.13
Summary: A Python client for the Ex Libris Alma REST APIs
License: MIT
Author: Tom Boone
Author-email: boone@wrlc.org
Requires-Python: >=3.11
Classifier: License :: OSI Approved :: MIT License
Classifier: Programming Language :: Python :: 3
Classifier: Programming Language :: Python :: 3.11
Classifier: Programming Language :: Python :: 3.12
Classifier: Programming Language :: Python :: 3.13
Requires-Dist: pydantic (>=2.11.4,<3.0.0)
Requires-Dist: requests (>=2.31.0,<3.0.0)
Requires-Dist: xmltodict (>=0.13.0,<0.15.0)
